LICENSE
README.md
setup.py
netradar/__init__.py
netradar/netradar.py
netradar/utils.py
netradar.egg-info/PKG-INFO
netradar.egg-info/SOURCES.txt
netradar.egg-info/dependency_links.txt
netradar.egg-info/requires.txt
netradar.egg-info/top_level.txt