Metadata-Version: 2.1
Name: netradar
Version: 0.2
Summary: NetRadars get you a way to interact with your network and scanning it.
Home-page: https://github.com/Eric-Canas/NetRadar
Author: Eric-Canas
Author-email: eric@ericcanas.com
License: MIT
Platform: UNKNOWN
Classifier: Development Status :: 2 - Pre-Alpha
Classifier: License :: OSI Approved :: MIT License
Classifier: Programming Language :: Python
Classifier: Programming Language :: Python :: 3
Classifier: Operating System :: OS Independent
Classifier: Intended Audience :: Developers
Classifier: Topic :: Software Development :: Libraries
Classifier: Topic :: Software Development :: Libraries :: Python Modules
Requires-Python: >=3.6
License-File: LICENSE
